{"schema":6,"addons":[{"id":"langpack-en-GB@thunderbird.mozilla.org","icons":{"32":"https://addons.thunderbird.net/static/img/addon-icons/default-32.png","64":"https://addons.thunderbird.net/static/img/addon-icons/default-64.png"},"name":"English (en-GB) Language Pack","version":"115.0.20230612.175521","sourceURI":"https://addons.thunderbird.net/thunderbird/downloads/file/1022069/english_en_gb_language_pack-115.0.20230612.175521-tb.xpi?src=","homepageURL":null,"supportURL":null,"description":"English (en-GB) Language Pack","fullDescription":null,"weeklyDownloads":1488,"type":"locale","creator":{"name":"Mozilla","url":"https://addons.thunderbird.net/en-US/thunderbird/user/mozilla/"},"developers":[],"screenshots":[],"contributionURL":"","averageRating":2.0968,"reviewCount":31,"reviewURL":"https://addons.thunderbird.net/en-US/thunderbird/addon/tb-langpack-en-gb/reviews/","updateDate":1686686405000},{"id":"langpack-en-CA@thunderbird.mozilla.org","icons":{"32":"https://addons.thunderbird.net/static/img/addon-icons/default-32.png","64":"https://addons.thunderbird.net/static/img/addon-icons/default-64.png"},"name":"English (en-CA) Language Pack","version":"115.0.20230612.175521","sourceURI":"https://addons.thunderbird.net/thunderbird/downloads/file/1022071/english_en_ca_language_pack-115.0.20230612.175521-tb.xpi?src=","homepageURL":null,"supportURL":null,"description":"English (en-CA) Language Pack","fullDescription":null,"weeklyDownloads":0,"type":"locale","creator":{"name":"Mozilla","url":"https://addons.thunderbird.net/en-US/thunderbird/user/mozilla/"},"developers":[],"screenshots":[],"contributionURL":"","averageRating":1,"reviewCount":1,"reviewURL":"https://addons.thunderbird.net/en-US/thunderbird/addon/tb-langpack-en-ca/reviews/","updateDate":1686686406000}]}